{
    "perfil": [
        {
            "lat": -17.458055555555557,
            "lon": -47.86833333333333,
            "elev": 962.0,
            "dist": 0.0
        },
        {
            "lat": -17.458263640611367,
            "lon": -47.86850691272829,
            "elev": 962.0,
            "dist": 0.02
        },
        {
            "lat": -17.458471725667174,
            "lon": -47.86868049212325,
            "elev": 962.0,
            "dist": 0.04
        },
        {
            "lat": -17.458679810722984,
            "lon": -47.86885407151821,
            "elev": 962.0,
            "dist": 0.06
        },
        {
            "lat": -17.458887895778794,
            "lon": -47.86902765091317,
            "elev": 962.0,
            "dist": 0.08
        },
        {
            "lat": -17.4590959808346,
            "lon": -47.86920123030813,
            "elev": 962.0,
            "dist": 0.1
        },
        {
            "lat": -17.45930406589041,
            "lon": -47.86937480970308,
            "elev": 962.0,
            "dist": 0.12
        },
        {
            "lat": -17.459512150946217,
            "lon": -47.86954838909804,
            "elev": 962.0,
            "dist": 0.14
        },
        {
            "lat": -17.459720236002028,
            "lon": -47.869721968493,
            "elev": 962.0,
            "dist": 0.16
        },
        {
            "lat": -17.459928321057838,
            "lon": -47.869895547887964,
            "elev": 962.0,
            "dist": 0.18
        },
        {
            "lat": -17.460136406113644,
            "lon": -47.87006912728292,
            "elev": 962.0,
            "dist": 0.2
        },
        {
            "lat": -17.460344491169455,
            "lon": -47.87024270667788,
            "elev": 962.0,
            "dist": 0.22
        },
        {
            "lat": -17.460552576225265,
            "lon": -47.87041628607284,
            "elev": 961.0,
            "dist": 0.24
        },
        {
            "lat": -17.46076066128107,
            "lon": -47.8705898654678,
            "elev": 960.0,
            "dist": 0.26
        },
        {
            "lat": -17.46096874633688,
            "lon": -47.87076344486275,
            "elev": 960.0,
            "dist": 0.28
        },
        {
            "lat": -17.46117683139269,
            "lon": -47.870937024257714,
            "elev": 961.0,
            "dist": 0.3
        },
        {
            "lat": -17.461384916448498,
            "lon": -47.871110603652674,
            "elev": 962.0,
            "dist": 0.32
        },
        {
            "lat": -17.46159300150431,
            "lon": -47.871284183047635,
            "elev": 962.0,
            "dist": 0.34
        },
        {
            "lat": -17.46180108656012,
            "lon": -47.87145776244259,
            "elev": 963.0,
            "dist": 0.36
        },
        {
            "lat": -17.462009171615925,
            "lon": -47.87163134183755,
            "elev": 963.0,
            "dist": 0.38
        },
        {
            "lat": -17.462217256671735,
            "lon": -47.87180492123251,
            "elev": 964.0,
            "dist": 0.4
        },
        {
            "lat": -17.462425341727542,
            "lon": -47.87197850062747,
            "elev": 964.0,
            "dist": 0.42
        },
        {
            "lat": -17.462633426783352,
            "lon": -47.872152080022424,
            "elev": 964.0,
            "dist": 0.44
        },
        {
            "lat": -17.462841511839162,
            "lon": -47.872325659417385,
            "elev": 963.0,
            "dist": 0.46
        },
        {
            "lat": -17.46304959689497,
            "lon": -47.872499238812345,
            "elev": 962.0,
            "dist": 0.48
        },
        {
            "lat": -17.46325768195078,
            "lon": -47.872672818207306,
            "elev": 962.0,
            "dist": 0.5
        },
        {
            "lat": -17.46346576700659,
            "lon": -47.87284639760226,
            "elev": 962.0,
            "dist": 0.52
        },
        {
            "lat": -17.463673852062396,
            "lon": -47.87301997699722,
            "elev": 962.0,
            "dist": 0.54
        },
        {
            "lat": -17.463881937118206,
            "lon": -47.87319355639218,
            "elev": 962.0,
            "dist": 0.56
        },
        {
            "lat": -17.464090022174016,
            "lon": -47.873367135787134,
            "elev": 962.0,
            "dist": 0.58
        },
        {
            "lat": -17.464298107229823,
            "lon": -47.873540715182095,
            "elev": 962.0,
            "dist": 0.6
        },
        {
            "lat": -17.464506192285633,
            "lon": -47.873714294577056,
            "elev": 962.0,
            "dist": 0.62
        },
        {
            "lat": -17.46471427734144,
            "lon": -47.873887873972016,
            "elev": 961.0,
            "dist": 0.64
        },
        {
            "lat": -17.46492236239725,
            "lon": -47.87406145336697,
            "elev": 961.0,
            "dist": 0.66
        },
        {
            "lat": -17.46513044745306,
            "lon": -47.87423503276193,
            "elev": 961.0,
            "dist": 0.68
        },
        {
            "lat": -17.465338532508866,
            "lon": -47.87440861215689,
            "elev": 961.0,
            "dist": 0.7
        },
        {
            "lat": -17.465546617564677,
            "lon": -47.87458219155185,
            "elev": 961.0,
            "dist": 0.72
        },
        {
            "lat": -17.465754702620487,
            "lon": -47.874755770946805,
            "elev": 960.0,
            "dist": 0.74
        },
        {
            "lat": -17.465962787676293,
            "lon": -47.874929350341766,
            "elev": 960.0,
            "dist": 0.76
        },
        {
            "lat": -17.466170872732103,
            "lon": -47.87510292973673,
            "elev": 960.0,
            "dist": 0.78
        },
        {
            "lat": -17.466378957787914,
            "lon": -47.87527650913169,
            "elev": 960.0,
            "dist": 0.8
        },
        {
            "lat": -17.46658704284372,
            "lon": -47.87545008852664,
            "elev": 960.0,
            "dist": 0.82
        },
        {
            "lat": -17.46679512789953,
            "lon": -47.8756236679216,
            "elev": 959.0,
            "dist": 0.84
        },
        {
            "lat": -17.46700321295534,
            "lon": -47.87579724731656,
            "elev": 959.0,
            "dist": 0.86
        },
        {
            "lat": -17.467211298011147,
            "lon": -47.87597082671152,
            "elev": 959.0,
            "dist": 0.88
        },
        {
            "lat": -17.467419383066957,
            "lon": -47.87614440610648,
            "elev": 959.0,
            "dist": 0.9
        },
        {
            "lat": -17.467627468122764,
            "lon": -47.87631798550144,
            "elev": 958.0,
            "dist": 0.92
        },
        {
            "lat": -17.467835553178574,
            "lon": -47.8764915648964,
            "elev": 958.0,
            "dist": 0.94
        },
        {
            "lat": -17.468043638234384,
            "lon": -47.87666514429136,
            "elev": 957.0,
            "dist": 0.96
        },
        {
            "lat": -17.46825172329019,
            "lon": -47.87683872368631,
            "elev": 957.0,
            "dist": 0.98
        },
        {
            "lat": -17.468459808346,
            "lon": -47.87701230308127,
            "elev": 956.0,
            "dist": 1.0
        }
    ],
    "bloqueio": null,
    "ponto_mais_alto": {
        "lat": -17.462217256671735,
        "lon": -47.87180492123251,
        "elev": 964.0
    }
}